{
  "name": "PulseChain",
  "shortName": "pls",
  "chain": "PLS",
  "chainId": 369,
  "networkId": 369,
  "infoURL": "https://pulsechain.com/",
  "rpc": [
    "https://pulsechain.publicnode.com"
  ],
  "features": [
    {
      "name": "EIP155"
    },
    {
      "name": "EIP1559"
    }
  ],
  "faucets": [],
  "ens": {
    "registry": "0x00000000000C2E074eC69A0dFb2997BA6C7d2e1e"
  },
  "status": "incubating",
  "nativeCurrency": {
    "name": "Pulse",
    "symbol": "PLS",
    "decimals": 18
  },
  "isDefault": false,
  "contract": {},
  "iconUrl": "https://raw.githubusercontent.com/tct68/icons/v2/assets/chains/rsz_pulse.jpg",
  "tvl": 125984911.97060737,
  "chainSlug": "pulse"
}