{
  "name": "DFK Chain",
  "chain": "DFK",
  "icon": "dfk",
  "rpc": [
    "https://avax-dfk.gateway.pokt.network/v1/lb/6244818c00b9f0003ad1b619/ext/bc/q2aTwKuyzgs8pynF7UXBZCU7DejbZbZ6EUyHr3JQzYgwNPUPi/rpc",
    "https://dfkchain.api.onfinality.io/public"
  ],
  "faucets": [],
  "nativeCurrency": {
    "name": "Jewel",
    "symbol": "JEWEL",
    "decimals": 18
  },
  "infoURL": "https://defikingdoms.com",
  "shortName": "DFK",
  "chainId": 53935,
  "networkId": 53935,
  "explorers": {
    "ethernal": "https://explorer.dfkchain.com"
  },
  "tokens": [],
  "isDefault": false,
  "contract": {}
}